findforce/__init__.py
findforce-0.0.1.dist-info/licenses/LICENSE
findforce-0.0.1.dist-info/METADATA
findforce-0.0.1.dist-info/WHEEL
findforce-0.0.1.dist-info/top_level.txt
findforce-0.0.1.dist-info/RECORD
